MANIFEST.in
README.md
setup.py
distruct/__init__.py
distruct/_diSTruct.cpp
distruct/_diSTruct.pyx
distruct/config.py
distruct/data.py
distruct/distructure.py
distruct/fileio.py
distruct/superimposer.py
distruct/topologydb.py
distruct.egg-info/PKG-INFO
distruct.egg-info/SOURCES.txt
distruct.egg-info/dependency_links.txt
distruct.egg-info/not-zip-safe
distruct.egg-info/requires.txt
distruct.egg-info/top_level.txt
distruct/share/1ptq.dist
distruct/share/amber99sb-ildn.xml
distruct/share/amber99sb-ildn_backbone.xml
distruct/share/amber99sb-ildn_heavy.xml
distruct/share/amber99sb-ildn_reduced.xml
distruct/share/convert.py
distruct/share/generate.py
distruct/share/tests/1ptq.pdb
distruct/share/tests/2gis.pdb
distruct/share/tests/3iqn.pdb
distruct/share/tests/test.ff/buildingblocks.rtp
distruct/share/tests/test.ff/ffbonded.itp
distruct/src/BioMaxentStress.cpp
distruct/src/BioMaxentStress.h
distruct/src/DuckingWrapper.h
distruct/src/aux/sig.h
distruct/tests/test_Distructure.py
distruct/tests/test_MaxEntStress.py
distruct/tests/test_distruct.py
distruct/tests/test_ffparsergmx.py
distruct/tests/test_fileio.py
distruct/tests/test_pdb.py
distruct/tests/test_superimposer.py
distruct/tools/__init__.py
distruct/tools/ffparsergmx.py
distruct/tools/math.py
distruct/tools/pdb.py