Metadata-Version: 2.1
Name: distruct
Version: 1.0.3
Summary: a package to generate 3d molecular structures from distance constraints
Home-page: https://github.com/KIT-MBS/distruct
Author: Oskar Taubert
Author-email: oskar.taubert@kit.edu
License: UNKNOWN
Download-URL: https://pypi.python.org/pypi/distruct
Keywords: biomolecules,graph drawing
Platform: UNKNOWN
Classifier: Programming Language :: Python :: 3
Classifier: Programming Language :: C++
Classifier: Environment :: Console
Classifier: Natural Language :: English
Classifier: License :: OSI Approved :: MIT License
Classifier: Operating System :: POSIX :: Linux
Classifier: Topic :: Scientific/Engineering :: Bio-Informatics
